{
    "speed_multiplier": 1.5,
    "typo_rate": 0.2,
    "hesitation_rate": 0.3,
    "overshoot_rate": 0.2,
    "distraction_rate": 0.2,
    "empty_click_rate": 0.05,
    "drag_rate": 0.4,
    "batch_min": 3,
    "batch_max": 8,
    "break_min_sec": 180,
    "break_max_sec": 600,
    "work_start_hour": 9,
    "work_end_hour": 23,
    "weekend_skip_rate": 0.4,
    "fitts_law_enabled": 1.0,
    "micro_correction_rate": 0.3,
    "click_hesitation_rate": 0.5,
    "double_click_mistake": 0.05,
    "fatigue_factor": 0.1,
    "breathing_rate": 0.1,
    "gaze_simulation": 0.2,
    "mouse_leave_rate": 0.1
}